datasette_permissions_sql/__init__.py
datasette_permissions_sql-0.3a0.dist-info/LICENSE
datasette_permissions_sql-0.3a0.dist-info/METADATA
datasette_permissions_sql-0.3a0.dist-info/WHEEL
datasette_permissions_sql-0.3a0.dist-info/entry_points.txt
datasette_permissions_sql-0.3a0.dist-info/top_level.txt
datasette_permissions_sql-0.3a0.dist-info/RECORD
