Metadata-Version: 2.1
Name: datasette-permissions-sql
Version: 0.3a0
Summary: Datasette plugin for configuring permission checks using SQL queries
Home-page: https://github.com/simonw/datasette-permissions-sql
Author: Simon Willison
License: Apache License, Version 2.0
Platform: UNKNOWN
Requires-Dist: datasette (>=0.44)
Provides-Extra: test
Requires-Dist: pytest ; extra == 'test'
Requires-Dist: pytest-asyncio ; extra == 'test'
Requires-Dist: httpx ; extra == 'test'
Requires-Dist: sqlite-utils (~=2.0) ; extra == 'test'
